golix/__init__.py
golix/_getlow.py
golix/_spec.py
golix/cipher.py
golix/core.py
golix/crypto_utils.py
golix/exceptions.py
golix/utils.py
golix-0.1.6.dist-info/DESCRIPTION.rst
golix-0.1.6.dist-info/METADATA
golix-0.1.6.dist-info/RECORD
golix-0.1.6.dist-info/WHEEL
golix-0.1.6.dist-info/metadata.json
golix-0.1.6.dist-info/top_level.txt
