Metadata-Version: 2.0
Name: golix
Version: 0.1.6
Summary: A python library for Golix object manipulation.
Home-page: https://github.com/Muterra/py_golix
Author: Muterra, Inc
Author-email: badg@muterra.io
License: LGPL
Keywords: golix,encryption,security,privacy,private,identity,sharing
Platform: UNKNOWN
Classifier: Development Status :: 3 - Alpha
Classifier: Intended Audience :: Developers
Classifier: Topic :: Software Development
Classifier: Topic :: Utilities
Classifier: License :: OSI Approved :: GNU Lesser General Public License v2 or later (LGPLv2+)
Classifier: Programming Language :: Python :: 3.5
Provides-Extra: full
Requires-Dist: cryptography (>=1.6); extra == 'full'
Requires-Dist: donna25519 (>=0.1.1); extra == 'full'
Requires-Dist: smartyparse (>=0.1.3); extra == 'full'
